pyavwx/__init__.py
pyavwx/avwx_authentication.py
pyavwx/avwx_client.py
pyavwx/avwx_exceptions.py
pyavwx/avwx_requests_manager.py
pyavwx/const.py
pyavwx/models/__init__.py
pyavwx/models/airSigmet.py
pyavwx/models/exceptions.py
pyavwx/models/metar.py
pyavwx/models/nbm_gfs.py
pyavwx/models/notams.py
pyavwx/models/pirep.py
pyavwx/models/station.py
pyavwx/models/structs.py
pyavwx/models/summary.py
pyavwx/models/taf.py
pyavwx/models/utils.py
pyavwx_wrapper-0.3.3.dist-info/licenses/LICENSE
pyavwx_wrapper-0.3.3.dist-info/METADATA
pyavwx_wrapper-0.3.3.dist-info/WHEEL
pyavwx_wrapper-0.3.3.dist-info/top_level.txt
pyavwx_wrapper-0.3.3.dist-info/RECORD
